rudiments/__init__.py
rudiments/_compat.py
rudiments/humanize.py
rudiments/morph.py
rudiments/pysupport.py
rudiments/security.py
rudiments/system.py
rudiments/www.py
rudiments/reamed/__init__.py
rudiments/reamed/click.py
rudiments-0.4.1.data/data/EGG-INFO/LICENSE
rudiments-0.4.1.data/data/EGG-INFO/README.md
rudiments-0.4.1.dist-info/LICENSE
rudiments-0.4.1.dist-info/METADATA
rudiments-0.4.1.dist-info/WHEEL
rudiments-0.4.1.dist-info/entry_points.txt
rudiments-0.4.1.dist-info/top_level.txt
rudiments-0.4.1.dist-info/RECORD
